oat/__init__.py
oat/cli.py
oat/compiler.py
oat/config.py
oat/constants.py
oat/discovery.py
oat/template_manager.py
oat/validator.py
oat/templates/.oat-root
oat/templates/AGENTS.md
oat/templates/__init__.py
oat/templates/inherits.yaml
oat/templates/project.md
oat/templates/memory/constitution.md
oat/templates/memory/general-context.md
oat/templates/memory/manifest.yaml
oat/templates/memory/personal-context.md
oat/templates/personas/backend-developer.md
oat/templates/personas/devops.md
oat/templates/personas/frontend-developer.md
oat/templates/personas/me.md
oat/templates/personas/qa.md
oat/templates/personas/tech-lead.md
oat/templates/skills/db.md
oat/templates/skills/git.md
oat/templates/skills/review-checklist.md
oat/templates/skills/test.md
oat/templates/skills/go/go.md
oat/templates/skills/java/java.md
oat/templates/skills/javascript/jest.md
oat/templates/skills/javascript/nodejs.md
oat/templates/skills/javascript/react.md
oat/templates/skills/python/django.md
oat/templates/skills/python/fastapi.md
oat/templates/skills/python/pytest.md
oat/templates/skills/python/python.md
oat/templates/skills/python/uv.md
oat/templates/skills/rust/rust.md
oat/templates/teams/_template.md
oat/templates/teams/platform.md
oat/templates/teams/product.md
oat/templates/toolkit/README.md
oat/templates/toolkit/oat
oat/templates/toolkit/targets.yaml
oat/templates/toolkit/schemas/inherits.schema.json
oat/templates/toolkit/schemas/manifest.schema.json
oat/templates/toolkit/templates/AGENTS.md.template
oat/templates/toolkit/templates/inherits.yaml.template
oat/templates/toolkit/templates/project.md.template
oat/templates/toolkit/templates/project/AGENTS.md
oat/templates/toolkit/templates/project/.agent/inherits.yaml
oat/templates/toolkit/templates/project/.agent/project.md
org_agentic_toolkit-1.1.1.dist-info/METADATA
org_agentic_toolkit-1.1.1.dist-info/WHEEL
org_agentic_toolkit-1.1.1.dist-info/entry_points.txt
org_agentic_toolkit-1.1.1.dist-info/top_level.txt
org_agentic_toolkit-1.1.1.dist-info/RECORD
