Metadata-Version: 2.4
Name: org-agentic-toolkit
Version: 1.1.1
Summary: Governance infrastructure that compiles and validates organization-level agent rules
Author: Alain Prasquier [alain-sv](https://github.com/alain-sv/)
License: MIT
Keywords: agent,governance,rules,compilation,validation
Classifier: Development Status :: 4 - Beta
Classifier: Intended Audience :: Developers
Classifier: License :: OSI Approved :: MIT License
Classifier: Programming Language :: Python :: 3
Classifier: Programming Language :: Python :: 3.11
Classifier: Programming Language :: Python :: 3.12
Requires-Python: >=3.12
Requires-Dist: pyyaml>=6.0
Requires-Dist: click>=8.3.0
Requires-Dist: questionary>=2.1.1
Provides-Extra: dev
Requires-Dist: pytest>=9.0.0; extra == "dev"
Requires-Dist: pytest-cov>=7.0.0; extra == "dev"
Requires-Dist: jsonschema>=4.0.0; extra == "dev"
Requires-Dist: watchdog>=6.0.0; extra == "dev"
